localcrawl/__init__.py
localcrawl/cli.py
localcrawl/crawler.py
localcrawl/scraper.py
localcrawl-0.2.3.dist-info/METADATA
localcrawl-0.2.3.dist-info/RECORD
localcrawl-0.2.3.dist-info/WHEEL
localcrawl-0.2.3.dist-info/entry_points.txt
localcrawl-0.2.3.dist-info/top_level.txt
