Metadata-Version: 2.1
Name: localcrawl
Version: 0.2.3
Summary: Crawl rendered JavaScript templates from a local server.
Home-page: https://github.com/svenkreiss/localcrawl
Author: Sven Kreiss
Author-email: me@svenkreiss.com
License: MIT
Platform: UNKNOWN
Classifier: Development Status :: 3 - Alpha
Classifier: Intended Audience :: Developers
Classifier: Intended Audience :: Science/Research
Classifier: Natural Language :: English
Classifier: License :: OSI Approved :: MIT License
Classifier: Operating System :: OS Independent
Classifier: Programming Language :: Python
Classifier: Programming Language :: Python :: 2.7
Classifier: Programming Language :: Python :: 3.4
Classifier: Programming Language :: Python :: 3.5
Classifier: Programming Language :: Python :: 3.6
Classifier: Programming Language :: Python :: Implementation :: PyPy
Provides-Extra: tests
Requires-Dist: selenium (>=2.53.6)
Provides-Extra: tests
Requires-Dist: hacking (>=0.11.0); extra == 'tests'
Requires-Dist: nose (>=1.3.4); extra == 'tests'
